{"skeleton":{"hash":"RnfRFLWeGVy9x+qS6TlnYOCPfzI","spine":"3.8.95","x":-341,"y":-459,"width":682,"height":918,"images":"./1_49_26/","audio":"E:/Art/81-100/93_安妮49/1_49_26"},"bones":[{"name":"root"},{"name":"bone","parent":"root"},{"name":"st","parent":"bone","x":128.37,"y":-330.28},{"name":"zs","parent":"st","length":52.36,"rotation":162.97,"x":4.36,"y":65.47},{"name":"bone2","parent":"st","x":48.91,"y":-8.78},{"name":"bone3","parent":"bone2","length":44.52,"rotation":58.64},{"name":"bone4","parent":"bone3","length":45.08,"rotation":12.92,"x":44.52},{"name":"bone5","parent":"bone4","length":38.94,"rotation":-50.09,"x":45.08},{"name":"3shoudiantong","parent":"zs","x":79.44,"y":-15.26},{"name":"sdt","parent":"3shoudiantong","length":139.1,"rotation":-15.65,"x":29.52,"y":-9.18},{"name":"ys","parent":"st","length":38.68,"rotation":-60.75,"x":33.86,"y":60.92},{"name":"t","parent":"st","length":56.24,"rotation":69.92,"x":17.79,"y":87.8}],"slots":[{"name":"root","bone":"root","attachment":"root"},{"name":"ditu","bone":"bone","attachment":"ditu"},{"name":"1diban","bone":"bone","attachment":"1diban"},{"name":"1xiangkuang1","bone":"bone","attachment":"1xiangkuang1"},{"name":"1xiangkuang2","bone":"bone","attachment":"1xiangkuang2"},{"name":"1xiangkuang3","bone":"bone","attachment":"1xiangkuang3"},{"name":"1xiangkuang4","bone":"bone","attachment":"1xiangkuang4"},{"name":"1xiangkuang5","bone":"bone","attachment":"1xiangkuang5"},{"name":"1xiangkuang6","bone":"bone","attachment":"1xiangkuang6"},{"name":"1xiangkuang7","bone":"bone","attachment":"1xiangkuang7"},{"name":"ty1","bone":"bone","attachment":"ty1"},{"name":"2zhuangshi1","bone":"bone","attachment":"2zhuangshi1"},{"name":"2zhuangshi2","bone":"bone","attachment":"2zhuangshi2"},{"name":"2zhuangshi3","bone":"bone","attachment":"2zhuangshi3"},{"name":"2zhuangshi4","bone":"bone","attachment":"2zhuangshi4"},{"name":"2xiangpian3","bone":"bone","attachment":"2xiangpian3"},{"name":"2xiangpian5","bone":"bone","attachment":"2xiangpian5"},{"name":"2xiangpian6","bone":"bone","attachment":"2xiangpian6"},{"name":"2xiangpian7","bone":"bone","attachment":"2xiangpian7"},{"name":"2chuanglianyou","bone":"bone","attachment":"2chuanglianyou"},{"name":"2chuanglianzuo","bone":"bone","attachment":"2chuanglianzuo"},{"name":"2songshu","bone":"bone","attachment":"2songshu"},{"name":"ty2","bone":"bone","attachment":"ty2"},{"name":"3maozi","bone":"bone","attachment":"3maozi"},{"name":"3xianglian","bone":"bone","attachment":"3xianglian"},{"name":"3bolibei","bone":"bone","attachment":"3bolibei"},{"name":"3shoudiantong","bone":"3shoudiantong","attachment":"3shoudiantong"},{"name":"3songshu","bone":"bone"},{"name":"3weilan","bone":"bone","attachment":"3weilan"},{"name":"3paizi","bone":"bone","attachment":"3paizi"},{"name":"ty3","bone":"bone","attachment":"ty3"},{"name":"xg1","bone":"bone"},{"name":"xg2","bone":"bone"},{"name":"xg3","bone":"bone"},{"name":"g","bone":"bone","attachment":"g"},{"name":"sdt","bone":"sdt","attachment":"sdt"},{"name":"ys","bone":"ys","attachment":"ys"},{"name":"st","bone":"st","attachment":"st"},{"name":"t","bone":"t","attachment":"t"},{"name":"wb","bone":"bone","attachment":"wb"},{"name":"zs","bone":"zs","attachment":"zs"},{"name":"zzw","bone":"bone","attachment":"zzw"}],"skins":[{"name":"default","attachments":{"1diban":{"1diban":{"y":-404,"width":682,"height":110}},"1xiangkuang1":{"1xiangkuang1":{"y":103.5,"width":324,"height":469}},"1xiangkuang2":{"1xiangkuang2":{"x":297.5,"y":320.5,"width":87,"height":277}},"1xiangkuang3":{"1xiangkuang3":{"x":269,"y":36.5,"width":102,"height":169}},"1xiangkuang4":{"1xiangkuang4":{"x":-20,"y":435,"width":304,"height":48}},"1xiangkuang5":{"1xiangkuang5":{"x":-284.5,"y":250.5,"width":113,"height":367}},"1xiangkuang6":{"1xiangkuang6":{"x":-260.5,"y":-120,"width":111,"height":200}},"1xiangkuang7":{"1xiangkuang7":{"x":267.5,"y":-159.5,"width":147,"height":123}},"2chuanglianyou":{"2chuanglianyou":{"x":83.5,"y":183,"width":107,"height":252}},"2chuanglianzuo":{"2chuanglianzuo":{"x":-88.5,"y":190.5,"width":103,"height":239}},"2songshu":{"2songshu":{"x":1.5,"y":65,"width":265,"height":332}},"2xiangpian3":{"2xiangpian3":{"x":269,"y":37,"width":76,"height":138}},"2xiangpian5":{"2xiangpian5":{"x":-295.5,"y":253.5,"width":91,"height":315}},"2xiangpian6":{"2xiangpian6":{"x":-259.5,"y":-121,"width":85,"height":170}},"2xiangpian7":{"2xiangpian7":{"x":276.5,"y":-160,"width":129,"height":88}},"2zhuangshi1":{"2zhuangshi1":{"y":362,"width":376,"height":68}},"2zhuangshi2":{"2zhuangshi2":{"y":-163,"width":294,"height":76}},"2zhuangshi3":{"2zhuangshi3":{"x":180,"y":101,"width":60,"height":454}},"2zhuangshi4":{"2zhuangshi4":{"x":-178,"y":101,"width":60,"height":454}},"3bolibei":{"3bolibei":{"x":-92.5,"y":66.5,"width":29,"height":91}},"3maozi":{"3maozi":{"y":127,"width":136,"height":214}},"3paizi":{"3paizi":{"x":-102,"y":-229.5,"width":118,"height":51}},"3shoudiantong":{"3shoudiantong":{"x":-3.41,"y":-4.45,"rotation":-155.18,"width":74,"height":64}},"3weilan":{"3weilan":{"y":-347.5,"width":682,"height":223}},"3xianglian":{"3xianglian":{"x":-9,"y":30,"width":82,"height":76}},"ditu":{"ditu":{"type":"mesh","uvs":[1,1,0,1,0,0,1,0],"triangles":[1,2,3,1,3,0],"vertices":[341,-459,-341,-459,-341,459,341,459],"hull":4,"edges":[0,2,2,4,4,6,0,6],"width":682,"height":918}},"g":{"g":{"x":-146.12,"y":96.74,"width":383,"height":641}},"root":{"root":{"type":"clipping","end":"root","vertexCount":4,"vertices":[-341,459,341,459,341,-459,-341,-459],"color":"ce3a3aff"}},"sdt":{"sdt":{"x":235.2,"y":-55.86,"rotation":-139.53,"width":484,"height":658}},"st":{"st":{"x":-11.48,"y":6.46,"width":131,"height":181}},"t":{"t":{"x":73.1,"y":-0.39,"rotation":-69.92,"width":173,"height":146}},"ty1":{"ty1":{"y":115,"width":682,"height":688}},"ty2":{"ty2":{"x":29.5,"y":90,"width":365,"height":586}},"ty3":{"ty3":{"x":131.5,"y":-136.5,"width":391,"height":583}},"wb":{"wb":{"type":"mesh","uvs":[1,1,0.66667,1,0.33333,1,0,1,0,0.8,0,0.6,0,0.4,0,0.2,0,0,0.33333,0,0.66667,0,1,0,1,0.2,1,0.4,1,0.6,1,0.8,0.66667,0.8,0.33333,0.8,0.66667,0.6,0.33333,0.6,0.66667,0.4,0.33333,0.4,0.66667,0.2,0.33333,0.2],"triangles":[3,4,17,4,5,19,19,5,21,23,9,10,22,23,10,20,21,22,22,10,11,12,22,11,20,22,12,13,20,12,18,20,13,14,18,13,7,8,9,23,7,9,6,7,23,21,6,23,5,6,21,21,23,22,19,21,20,17,4,19,2,3,17,18,19,20,17,19,18,16,17,18,2,17,16,1,2,16,16,18,14,15,16,14,1,16,15,0,1,15],"vertices":[3,5,20.39,-113.84,0.65191,6,-48.97,-105.56,0.27044,7,20.62,-139.87,0.07765,3,5,-2.33,-76.55,0.77997,6,-62.78,-64.13,0.1795,7,-20.01,-123.88,0.04053,4,5,-25.05,-39.26,0.84157,6,-76.59,-22.71,0.02083,7,-60.65,-107.89,0.0016,4,20.49,-41.82,0.136,2,5,-47.78,-1.97,0.584,4,-23.18,-41.82,0.416,1,4,-23.18,-7.82,1,1,4,-23.18,26.18,1,4,5,39.33,51.11,0.37714,6,6.37,50.98,0.46108,7,-63.94,3.01,0.00178,4,-23.18,60.18,0.16,3,5,68.36,68.8,0.09643,6,38.62,61.73,0.79094,7,-51.49,34.65,0.11263,3,5,97.39,86.49,0.01353,6,70.88,72.48,0.74273,7,-39.04,66.29,0.24374,3,5,120.12,49.21,2.1E-4,6,84.69,31.05,0.39104,7,1.59,50.3,0.60875,2,6,98.5,-10.37,0.00267,7,42.23,34.32,0.99733,2,6,112.3,-51.8,0,7,82.86,18.33,1,3,5,136.53,-43.06,0.0013,6,80.05,-62.55,0.02986,7,70.41,-13.31,0.96884,3,5,107.49,-60.76,0.0605,6,47.79,-73.3,0.24298,7,57.97,-44.95,0.69652,3,5,78.46,-78.45,0.27597,6,15.54,-84.05,0.38546,7,45.52,-76.59,0.33857,3,5,49.43,-96.14,0.54098,6,-16.72,-94.81,0.3221,7,33.07,-108.23,0.13691,3,5,26.7,-58.85,0.68402,6,-30.52,-53.38,0.24425,7,-7.57,-92.24,0.07174,4,5,3.98,-21.56,0.84247,6,-44.33,-11.95,0.01894,7,-48.2,-76.25,0.00259,4,20.49,-7.82,0.136,3,5,55.74,-41.16,0.33299,6,1.73,-42.63,0.48215,7,4.88,-60.6,0.18486,3,5,33.01,-3.87,0.86261,7,-35.75,-44.61,0.00139,4,20.49,26.18,0.136,3,5,84.77,-23.47,0.0255,6,33.99,-31.88,0.45468,7,17.33,-28.96,0.51981,2,5,62.05,13.82,0.0667,6,20.18,9.55,0.9333,1,7,29.78,2.68,1,3,5,91.08,31.51,0.01366,6,52.43,20.3,0.62283,7,-10.86,18.66,0.36351],"hull":16,"edges":[0,2,2,4,4,6,6,8,8,10,10,12,12,14,14,16,16,18,18,20,20,22,22,24,24,26,26,28,28,30,30,0],"width":131,"height":170}},"ys":{"ys":{"x":19.32,"y":3.85,"rotation":60.75,"width":51,"height":88}},"zs":{"zs":{"x":21.92,"y":5.5,"rotation":-155.18,"width":96,"height":76}},"zzw":{"zzw":{"x":16.66,"y":215.2,"width":492,"height":444}}}}],"animations":{"animation":{"bones":{"t":{"rotate":[{"curve":0.279,"c3":0.622,"c4":0.39},{"time":0.7667,"angle":-7.99,"curve":"stepped"},{"time":1.7,"angle":-7.99,"curve":0.328,"c2":0.32,"c3":0.758},{"time":2.3667}]},"zs":{"rotate":[{"curve":0,"c3":0.75},{"time":0.6667,"angle":-9.23,"curve":"stepped"},{"time":1.5667,"angle":-9.23,"curve":0,"c3":0.75},{"time":2.3333}]},"bone3":{"rotate":[{"angle":-1.89,"curve":0.379,"c2":0.6,"c3":0.723},{"time":0.4,"curve":0.25,"c3":0.75},{"time":2.0667,"angle":-10.87,"curve":0.242,"c3":0.669,"c4":0.68},{"time":3.3333,"angle":-1.89}]},"bone4":{"rotate":[{"angle":-5.15,"curve":0.377,"c2":0.51,"c3":0.749},{"time":0.8,"curve":0.25,"c3":0.75},{"time":2.4667,"angle":-10.87,"curve":0.249,"c3":0.627,"c4":0.51},{"time":3.3333,"angle":-5.15}]},"bone5":{"rotate":[{"angle":-8.51,"curve":0.34,"c2":0.36,"c3":0.757},{"time":1.2,"curve":0.25,"c3":0.75},{"time":2.8667,"angle":-10.87,"curve":0.272,"c3":0.619,"c4":0.41},{"time":3.3333,"angle":-8.51}]}}}}}